abel/__init__.py
abel/abel.py
abel/utils.py
abel_pytorch-0.0.1.dist-info/LICENSE
abel_pytorch-0.0.1.dist-info/METADATA
abel_pytorch-0.0.1.dist-info/WHEEL
abel_pytorch-0.0.1.dist-info/top_level.txt
abel_pytorch-0.0.1.dist-info/RECORD
