Metadata-Version: 2.1
Name: abel-pytorch
Version: 0.0.1
Summary: ABEL Scheduler
Home-page: https://github.com/tourdeml/abel-pytorch
Author: Vaibhav Balloli
Author-email: balloli.vb@gmail.com
License: MIT
Keywords: learning rate,pytorch
Platform: UNKNOWN
Classifier: Development Status :: 4 - Beta
Classifier: Intended Audience :: Developers
Classifier: Topic :: Scientific/Engineering :: Artificial Intelligence
Classifier: License :: OSI Approved :: MIT License
Classifier: Programming Language :: Python :: 3.6
Classifier: Programming Language :: Python :: 3.7
Classifier: Programming Language :: Python :: 3.8
